zpz/__init__.py
zpz/avro.py
zpz/aws_s3.py
zpz/bokeh.py
zpz/config.py
zpz/dask.py
zpz/datetime.py
zpz/email.py
zpz/iter.py
zpz/list.py
zpz/logging.py
zpz/notify.py
zpz/pandas.py
zpz/path.py
zpz/profile.py
zpz/s3.py
zpz/serde.py
zpz/slack.py
zpz/spark.py
zpz/teleshell.py
zpz/text.py
zpz/version.py
zpz/sql/__init__.py
zpz/sql/athena.py
zpz/sql/hive.py
zpz/sql/mysql.py
zpz/sql/mysqlalchemy.py
zpz/sql/postgres.py
zpz/sql/sql.py
zpz/sql/util.py
zpz-0.18.1.dist-info/LICENSE
zpz-0.18.1.dist-info/METADATA
zpz-0.18.1.dist-info/WHEEL
zpz-0.18.1.dist-info/top_level.txt
zpz-0.18.1.dist-info/RECORD
