Metadata-Version: 2.1
Name: zpz
Version: 0.18.1
Summary: Various Python utilities
Home-page: https://github.com/zpz/utilities.py
License: BSD
Platform: UNKNOWN
Classifier: License :: OSI Approved :: BSD License
Classifier: Programming Language :: Python :: 3
Classifier: Programming Language :: Python :: 3.6
